<PAMDataset>
  <PAMRasterBand band="1">
    <Histograms>
      <HistItem>
        <HistMin>-2.290974532455206</HistMin>
        <HistMax>0.705433462947607</HistMax>
        <BucketCount>1000</BucketCount>
        <IncludeOutOfRange>0</IncludeOutOfRange>
        <Approximate>0</Approximate>
        <HistCounts>0|0|0|0|0|0|0|0|0|0|0|0|0|0|0|0|0|0|0|0|0|0|0|0|0|0|0|0|0|0|0|0|0|0|0|0|0|0|0|0|0|0|0|0|0|0|0|0|0|0|0|0|0|0|0|0|0|0|0|0|0|0|0|0|0|0|0|0|0|0|0|0|0|0|0|0|0|0|0|0|0|0|0|0|0|0|0|0|0|0|0|0|0|0|0|0|0|0|0|0|0|0|0|0|0|0|0|0|0|0|0|0|0|0|0|0|0|0|0|0|0|0|0|0|0|0|0|0|0|0|0|0|0|0|0|0|0|0|0|0|0|0|0|0|0|0|0|0|0|0|0|0|0|0|0|0|0|0|0|0|0|0|0|0|0|0|0|0|0|0|0|0|0|0|0|0|0|0|0|0|0|0|0|0|0|0|0|0|0|0|0|0|0|0|0|0|0|0|0|0|0|0|0|0|0|0|0|0|0|0|0|0|0|0|0|0|0|0|0|0|0|0|0|0|0|0|0|0|0|0|0|0|0|0|0|0|0|0|0|0|0|0|0|0|0|0|0|0|0|0|0|0|0|0|0|0|0|0|0|0|0|0|0|0|0|0|0|0|0|0|0|0|0|0|0|0|0|0|0|0|0|0|0|0|0|0|0|0|0|0|0|0|0|0|0|0|0|0|0|0|0|0|0|0|0|0|0|0|0|0|0|0|0|0|0|0|0|0|0|0|0|0|0|0|0|0|0|0|0|0|0|0|0|0|0|0|0|0|0|0|0|0|0|0|0|0|0|0|0|0|0|0|0|0|0|0|0|0|0|0|0|0|0|0|0|0|0|0|0|0|0|0|0|0|0|0|0|0|0|0|0|0|0|0|0|0|0|0|0|0|0|0|0|0|0|0|0|0|0|0|0|0|0|0|0|0|0|0|0|0|0|0|0|0|0|0|0|0|0|0|0|0|0|0|0|0|0|0|0|0|0|0|0|0|0|0|0|0|0|0|0|0|0|0|0|0|0|0|0|0|0|0|0|0|0|0|0|0|0|0|0|0|0|0|0|0|0|0|0|0|0|0|0|0|0|0|0|0|0|0|0|0|0|0|0|0|0|0|0|0|0|0|0|0|0|0|0|0|0|0|0|0|0|0|0|0|0|0|0|0|0|0|0|0|0|0|0|0|0|0|0|0|0|0|0|0|0|0|0|0|0|0|0|0|0|0|0|0|0|0|0|0|0|0|0|0|0|0|0|0|0|0|0|0|0|0|0|0|0|0|0|0|0|0|0|0|0|0|0|0|0|0|0|0|0|0|0|0|0|0|0|0|0|0|0|0|0|0|0|0|0|0|0|0|0|0|0|0|0|0|0|0|0|0|0|0|0|0|0|0|0|0|0|0|0|0|0|0|0|0|0|0|0|0|0|0|0|0|0|0|0|0|0|0|0|0|0|0|0|0|0|0|0|0|0|0|0|0|0|0|0|0|0|0|0|0|0|0|0|0|0|0|0|0|0|0|0|0|0|0|0|0|0|0|0|0|0|0|0|0|0|0|0|0|0|0|0|0|0|0|0|0|0|0|0|0|0|0|0|0|0|0|0|0|0|0|0|0|0|0|0|0|0|0|0|0|0|0|0|0|0|0|0|0|0|0|0|0|0|0|0|0|0|0|0|0|0|0|0|0|0|0|0|0|0|0|0|0|0|0|0|0|0|0|0|0|0|0|0|0|0|0|0|0|100|244|221|248|235|226|215|224|220|230|225|239|247|224|254|234|261|258|245|240|293|236|284|315|369|321|266|316|281|309|303|319|295|297|275|275|237|257|227|244|248|236|252|294|323|279|279|260|296|238|267|277|254|254|287|281|261|282|297|306|342|319|326|319|338|352|363|353|357|358|399|433|386|407|403|406|408|417|424|453|468|558|548|504|513|492|530|594|594|551|543|528|516|535|500|499|459|453|440|452|450|418|427|380|403|340|345|310|327|330|321|333|329|342|317|330|342|351|359|425|542|613|819|636|552|548|511|407|397|354|349|322|303|285|312|266|259|256|269|223|245|230|204|211|206|205|198|199|190|180|194|170|173|172|148|192|165|158|172|138|151|138|130|151|148|132|150|157|129|138|138|114|123|123|129|115|110|137|106|129|118|106|120|115|112|120|121|123|103|81|81|79|86|57|77|76|74|66|71|60|71|86|63|59|71|78|68|75|57|68|68|72|72|64|58|75|70|63|50|60|74|73|60|54|51|56|50|53|38|55|48|55|51|46|51|45</HistCounts>
      </HistItem>
    </Histograms>
    <Metadata>
      <MDI key="COLOR_TABLE_RULE_RGB_0">-2.289478e+000 -1.690795e+000 0 191 191 0 255 0</MDI>
      <MDI key="COLOR_TABLE_RULE_RGB_1">-1.690795e+000 -1.092112e+000 0 255 0 255 255 0</MDI>
      <MDI key="COLOR_TABLE_RULE_RGB_2">-1.092112e+000 -4.934291e-001 255 255 0 255 127 0</MDI>
      <MDI key="COLOR_TABLE_RULE_RGB_3">-4.934291e-001 1.052538e-001 255 127 0 191 127 63</MDI>
      <MDI key="COLOR_TABLE_RULE_RGB_4">1.052538e-001 7.039367e-001 191 127 63 20 20 20</MDI>
      <MDI key="COLOR_TABLE_RULES_COUNT">5</MDI>
      <MDI key="STATISTICS_MAXIMUM">0.7039367556572</MDI>
      <MDI key="STATISTICS_MEAN">-0.01825561580833</MDI>
      <MDI key="STATISTICS_MINIMUM">-2.2894778251648</MDI>
      <MDI key="STATISTICS_STDDEV">0.58398235266583</MDI>
    </Metadata>
  </PAMRasterBand>
</PAMDataset>
